qcaas_client/__init__.py
qcaas_client/client.py
qcaas_client/commandline.py
oqc_qcaas_client-3.21.0.dist-info/LICENSE
oqc_qcaas_client-3.21.0.dist-info/METADATA
oqc_qcaas_client-3.21.0.dist-info/WHEEL
oqc_qcaas_client-3.21.0.dist-info/RECORD
